<?xml version='1.0' encoding='utf-8'?>
<Document xmlns="urn:iso:std:iso:20022:tech:xsd:pacs.002.001.10"><FIToFIPmtStsRpt><GrpHdr><MsgId>PACS002-ACSC-f275ba25</MsgId><CreDtTm>2025-09-30T16:00:00+00:00Z</CreDtTm></GrpHdr><OrgnlGrpInfAndSts><OrgnlMsgId>PAIN-2025-09-30-Public_Hospital_Dublin-159f05ed</OrgnlMsgId><OrgnlMsgNmId>pain.001.001.09</OrgnlMsgNmId><GrpSts>PART</GrpSts></OrgnlGrpInfAndSts><OrgnlPmtInfAndSts><OrgnlPmtInfId>PMTINF-2025-09-30-23bd43</OrgnlPmtInfId><TxInfAndSts><StsId>STS-72c6ac70</StsId><OrgnlInstrId>INST-20250930-00356</OrgnlInstrId><OrgnlEndToEndId>E2E-20250930-00356</OrgnlEndToEndId><TxSts>ACSC</TxSts><AccptncDtTm>2025-09-30T16:00:00+00:00Z</AccptncDtTm><OrgnlTxRef><Amt><InstdAmt Ccy="USD">2390.43</InstdAmt></Amt></OrgnlTxRef></TxInfAndSts><TxInfAndSts><StsId>STS-98f59b31</StsId><OrgnlInstrId>INST-20250930-00374</OrgnlInstrId><OrgnlEndToEndId>E2E-20250930-00374</OrgnlEndToEndId><TxSts>ACSC</TxSts><AccptncDtTm>2025-09-30T16:00:00+00:00Z</AccptncDtTm><OrgnlTxRef><Amt><InstdAmt Ccy="CAD">9536.48</InstdAmt></Amt></OrgnlTxRef></TxInfAndSts><TxInfAndSts><StsId>STS-91a67886</StsId><OrgnlInstrId>INST-20250930-00424</OrgnlInstrId><OrgnlEndToEndId>E2E-20250930-00424</OrgnlEndToEndId><TxSts>ACSC</TxSts><AccptncDtTm>2025-09-30T16:00:00+00:00Z</AccptncDtTm><OrgnlTxRef><Amt><InstdAmt Ccy="SEK">1127085.77</InstdAmt></Amt></OrgnlTxRef></TxInfAndSts></OrgnlPmtInfAndSts></FIToFIPmtStsRpt></Document>